pyproject.toml
setup.py
alignfig_estimator/__init__.py
alignfig_estimator/gain_data.py
alignfig_estimator.egg-info/PKG-INFO
alignfig_estimator.egg-info/SOURCES.txt
alignfig_estimator.egg-info/dependency_links.txt
alignfig_estimator.egg-info/requires.txt
alignfig_estimator.egg-info/top_level.txt